<?xml version="1.0" encoding="UTF-8"?>
<xml><thread id="21480"><title>Naked Female Gamers (e.g. Help wanted.)</title><posts><post id="p198186" date="Posted: Wed Apr 30, 2008 1:59 pm "><author>BloodRayne</author><body><![CDATA[<div class="postbody">(Sorry was the only way to get your attention hehe...)  <img src="https://web.archive.org/web/20101225103133im_/http://www.doom3world.org/phpbb2/images/smilies/icon_mrgreen.gif" alt=":mrgreen:" title="Mr. Green" /><br /><br /><img src="https://web.archive.org/web/20101225103133im_/http://img84.imageshack.us/img84/4396/bannertesttp4.jpg" alt="Image" /><br /><br />We're entering the final stages of development and are currently looking for mappers that can put 'oomph' in a map. <br />Don't hesitate, contact us now!</div>]]></body></post><post id="p198269" date="Posted: Thu May 01, 2008 7:57 am "><author>BloodRayne</author><body><![CDATA[<div class="postbody">Will bump this every now and then.</div>]]></body></post><post id="p198276" date="Posted: Thu May 01, 2008 12:33 pm "><author>lowdragon</author><body><![CDATA[<div class="postbody">I added my info. <img src="https://web.archive.org/web/20101225103133im_/http://www.doom3world.org/phpbb2/images/smilies/icon_smile.gif" alt=":)" title="Smile" /></div>]]></body></post><post id="p198332" date="Posted: Fri May 02, 2008 10:35 am "><author>BloodRayne</author><body><![CDATA[<div class="postbody">Yes, thank you got your email and replied! <img src="https://web.archive.org/web/20101225103133im_/http://www.doom3world.org/phpbb2/images/smilies/icon_smile.gif" alt=":)" title="Smile" /></div>]]></body></post><post id="p198333" date="Posted: Fri May 02, 2008 11:34 am "><author>LDAsh</author><body><![CDATA[<div class="postbody">Anywhere mappers might read up on exactly what sort of maps the project needs?  Seems like big SP maps are on the menu, but any need for say some small deathmatch arena type map that one might be able to do up in a week or two?  I'd like to do some medieval stuff, but don't have barrels of free time for massive SP layouts.</div>]]></body></post><post id="p198348" date="Posted: Mon May 05, 2008 10:48 pm "><author>BloodRayne</author><body><![CDATA[<div class="postbody">We do need dedicated mappers for working on large SP maps. Story is everything so the mapping and scriptwork do require more than 1 or 2 weeks time, unfortunately. We will start development on the multiplayer aspects of the game after the first episode is released, so we won't need any help in that regard for the moment.</div>]]></body></post><post id="p199554" date="Posted: Thu May 29, 2008 12:24 pm "><author>BloodRayne</author><body><![CDATA[<div class="postbody"><span style="font-weight: bold">We are still looking for mappers!</span><br /><br />Interested to join our fantastic team? You'll be part of an exciting team of professional individuals, while working on a fantastic project. <br /><br />Don't hesitate and apply!</div>]]></body></post><post id="p198186" date="Posted: Wed Apr 30, 2008 1:59 pm "><author>BloodRayne</author><body><![CDATA[<div class="postbody">(Sorry was the only way to get your attention hehe...)  <img src="https://web.archive.org/web/20101225104405im_/http://www.doom3world.org/phpbb2/images/smilies/icon_mrgreen.gif" alt=":mrgreen:" title="Mr. Green" /><br /><br /><img src="https://web.archive.org/web/20101225104405im_/http://img84.imageshack.us/img84/4396/bannertesttp4.jpg" alt="Image" /><br /><br />We're entering the final stages of development and are currently looking for mappers that can put 'oomph' in a map. <br />Don't hesitate, contact us now!</div>]]></body></post><post id="p198269" date="Posted: Thu May 01, 2008 7:57 am "><author>BloodRayne</author><body><![CDATA[<div class="postbody">Will bump this every now and then.</div>]]></body></post><post id="p198276" date="Posted: Thu May 01, 2008 12:33 pm "><author>lowdragon</author><body><![CDATA[<div class="postbody">I added my info. <img src="https://web.archive.org/web/20101225104405im_/http://www.doom3world.org/phpbb2/images/smilies/icon_smile.gif" alt=":)" title="Smile" /></div>]]></body></post><post id="p198332" date="Posted: Fri May 02, 2008 10:35 am "><author>BloodRayne</author><body><![CDATA[<div class="postbody">Yes, thank you got your email and replied! <img src="https://web.archive.org/web/20101225104405im_/http://www.doom3world.org/phpbb2/images/smilies/icon_smile.gif" alt=":)" title="Smile" /></div>]]></body></post><post id="p198333" date="Posted: Fri May 02, 2008 11:34 am "><author>LDAsh</author><body><![CDATA[<div class="postbody">Anywhere mappers might read up on exactly what sort of maps the project needs?  Seems like big SP maps are on the menu, but any need for say some small deathmatch arena type map that one might be able to do up in a week or two?  I'd like to do some medieval stuff, but don't have barrels of free time for massive SP layouts.</div>]]></body></post><post id="p198348" date="Posted: Mon May 05, 2008 10:48 pm "><author>BloodRayne</author><body><![CDATA[<div class="postbody">We do need dedicated mappers for working on large SP maps. Story is everything so the mapping and scriptwork do require more than 1 or 2 weeks time, unfortunately. We will start development on the multiplayer aspects of the game after the first episode is released, so we won't need any help in that regard for the moment.</div>]]></body></post><post id="p199554" date="Posted: Thu May 29, 2008 12:24 pm "><author>BloodRayne</author><body><![CDATA[<div class="postbody"><span style="font-weight: bold">We are still looking for mappers!</span><br /><br />Interested to join our fantastic team? You'll be part of an exciting team of professional individuals, while working on a fantastic project. <br /><br />Don't hesitate and apply!</div>]]></body></post><post id="p198186" date="Posted: Wed Apr 30, 2008 1:59 pm "><author>BloodRayne</author><body><![CDATA[<div class="postbody">(Sorry was the only way to get your attention hehe...)  <img src="https://web.archive.org/web/20101225104405im_/http://www.doom3world.org/phpbb2/images/smilies/icon_mrgreen.gif" alt=":mrgreen:" title="Mr. Green" /><br /><br /><img src="https://web.archive.org/web/20101225104405im_/http://img84.imageshack.us/img84/4396/bannertesttp4.jpg" alt="Image" /><br /><br />We're entering the final stages of development and are currently looking for mappers that can put 'oomph' in a map. <br />Don't hesitate, contact us now!</div>]]></body></post><post id="p198269" date="Posted: Thu May 01, 2008 7:57 am "><author>BloodRayne</author><body><![CDATA[<div class="postbody">Will bump this every now and then.</div>]]></body></post><post id="p198276" date="Posted: Thu May 01, 2008 12:33 pm "><author>lowdragon</author><body><![CDATA[<div class="postbody">I added my info. <img src="https://web.archive.org/web/20101225104405im_/http://www.doom3world.org/phpbb2/images/smilies/icon_smile.gif" alt=":)" title="Smile" /></div>]]></body></post><post id="p198332" date="Posted: Fri May 02, 2008 10:35 am "><author>BloodRayne</author><body><![CDATA[<div class="postbody">Yes, thank you got your email and replied! <img src="https://web.archive.org/web/20101225104405im_/http://www.doom3world.org/phpbb2/images/smilies/icon_smile.gif" alt=":)" title="Smile" /></div>]]></body></post><post id="p198333" date="Posted: Fri May 02, 2008 11:34 am "><author>LDAsh</author><body><![CDATA[<div class="postbody">Anywhere mappers might read up on exactly what sort of maps the project needs?  Seems like big SP maps are on the menu, but any need for say some small deathmatch arena type map that one might be able to do up in a week or two?  I'd like to do some medieval stuff, but don't have barrels of free time for massive SP layouts.</div>]]></body></post><post id="p198348" date="Posted: Mon May 05, 2008 10:48 pm "><author>BloodRayne</author><body><![CDATA[<div class="postbody">We do need dedicated mappers for working on large SP maps. Story is everything so the mapping and scriptwork do require more than 1 or 2 weeks time, unfortunately. We will start development on the multiplayer aspects of the game after the first episode is released, so we won't need any help in that regard for the moment.</div>]]></body></post><post id="p199554" date="Posted: Thu May 29, 2008 12:24 pm "><author>BloodRayne</author><body><![CDATA[<div class="postbody"><span style="font-weight: bold">We are still looking for mappers!</span><br /><br />Interested to join our fantastic team? You'll be part of an exciting team of professional individuals, while working on a fantastic project. <br /><br />Don't hesitate and apply!</div>]]></body></post></posts></thread></xml>
